README.md
setup.cfg
setup.py
hr_little_api/__init__.py
hr_little_api/builders.py
hr_little_api/functional.py
hr_little_api/json_api.py
hr_little_api/robot.py
hr_little_api/transport.py
hr_little_api.egg-info/PKG-INFO
hr_little_api.egg-info/SOURCES.txt
hr_little_api.egg-info/dependency_links.txt
hr_little_api.egg-info/entry_points.txt
hr_little_api.egg-info/requires.txt
hr_little_api.egg-info/top_level.txt
hr_little_api_examples/__init__.py
hr_little_api_examples/action_callbacks.py
hr_little_api_examples/actions.py
hr_little_api_examples/custom_animations.py
hr_little_api_examples/functional_api.py
hr_little_api_examples/functional_api_callbacks.py
hr_little_api_examples/sensors.py