Metadata-Version: 1.2
Name: hr-little-api
Version: 19.10.1
Summary: The Python API for controlling Hanson Robotics consumer robots
Home-page: https://github.com/hansonrobotics/hr-little-api
Author: Hanson Robotics Limited
Author-email: info@hansonrobotics.com
License: Apache License Version 2.0
Download-URL: https://github.com/hansonrobotics/hr-little-api/v19.10.1.tar.gz
Keywords: robotics,einstein,sophia,robot,AI
Platform: UNKNOWN
Classifier: Programming Language :: Python :: 3
Classifier: License :: OSI Approved :: Apache Software License
Classifier: Operating System :: OS Independent
Requires-Python: >=3.6
